pyvoicing/__init__.py
pyvoicing/chroma.py
pyvoicing/constants.py
pyvoicing/interval.py
pyvoicing/pitch.py
pyvoicing/py.typed
pyvoicing/rest.py
pyvoicing/spelling.py
pyvoicing/voicing.py
pyvoicing-0.1.4.dist-info/licenses/LICENSE
pyvoicing-0.1.4.dist-info/METADATA
pyvoicing-0.1.4.dist-info/WHEEL
pyvoicing-0.1.4.dist-info/top_level.txt
pyvoicing-0.1.4.dist-info/RECORD
