Metadata-Version: 2.4
Name: pyvoicing
Version: 0.1.4
Summary: A Python library for symbolic music analysis, focusing on chord voicings and tensions.
Author-email: Yukang Luo <yukangluo@yukangluo.com>
License: MIT License
Project-URL: Homepage, https://github.com/lyk91471872/PyVoicing
Project-URL: Bug Tracker, https://github.com/lyk91471872/PyVoicing/issues
Classifier: Development Status :: 3 - Alpha
Classifier: Programming Language :: Python :: 3
Classifier: Programming Language :: Python :: 3.10
Classifier: Programming Language :: Python :: 3.11
Classifier: Programming Language :: Python :: 3.12
Classifier: License :: OSI Approved :: MIT License
Classifier: Operating System :: OS Independent
Requires-Python: >=3.10
License-File: LICENSE
Dynamic: license-file
